matrix_log_handler/__init__.py
matrix_log_handler-0.3.1.dist-info/METADATA
matrix_log_handler-0.3.1.dist-info/RECORD
matrix_log_handler-0.3.1.dist-info/WHEEL
matrix_log_handler-0.3.1.dist-info/top_level.txt
