Metadata-Version: 2.1
Name: matrix-log-handler
Version: 0.3.1
Summary: Log handler sending messages to a Matrix room
Home-page: https://github.com/getbenchmarked/matrix-log-handler
Author: Gergely Polonkai
Author-email: gergely@polonkai.eu
License: UNKNOWN
Keywords: matrix,logging
Platform: UNKNOWN
Classifier: Development Status :: 4 - Beta
Classifier: Intended Audience :: Developers
Classifier: Intended Audience :: System Administrators
Classifier: License :: OSI Approved :: Apache Software License
Classifier: Natural Language :: English
Classifier: Operating System :: OS Independent
Classifier: Programming Language :: Python
Classifier: Programming Language :: Python :: 2
Classifier: Programming Language :: Python :: 3
Classifier: Topic :: Software Development :: Libraries
Requires-Dist: matrix-client (>=0.0.6)
